<annotation>
	<folder>data11</folder>
	<filename>20181210_095550.jpg</filename>
	<path>/media/trivu/data/DataScience/CV/dua/data11/20181210_095550.jpg</path>
	<source>
		<database>Unknown</database>
	</source>
	<size>
		<width>2268</width>
		<height>4032</height>
		<depth>3</depth>
	</size>
	<segmented>0</segmented>
	<object>
		<name>pineapple</name>
		<pose>Unspecified</pose>
		<truncated>0</truncated>
		<difficult>0</difficult>
		<bndbox>
			<xmin>931</xmin>
			<ymin>1907</ymin>
			<xmax>1331</xmax>
			<ymax>2401</ymax>
		</bndbox>
	</object>
</annotation>
