<annotation>
	<folder>data02</folder>
	<filename>20181210_093233.jpg</filename>
	<path>/home/cuong/Desktop/BKSEEING/Dua/data02/20181210_093233.jpg</path>
	<source>
		<database>Unknown</database>
	</source>
	<size>
		<width>2268</width>
		<height>4032</height>
		<depth>3</depth>
	</size>
	<segmented>0</segmented>
	<object>
		<name>pineapple</name>
		<pose>Unspecified</pose>
		<truncated>0</truncated>
		<difficult>0</difficult>
		<bndbox>
			<xmin>533</xmin>
			<ymin>1999</ymin>
			<xmax>900</xmax>
			<ymax>2549</ymax>
		</bndbox>
	</object>
	<object>
		<name>pineapple</name>
		<pose>Unspecified</pose>
		<truncated>0</truncated>
		<difficult>0</difficult>
		<bndbox>
			<xmin>1104</xmin>
			<ymin>1340</ymin>
			<xmax>1267</xmax>
			<ymax>1678</ymax>
		</bndbox>
	</object>
</annotation>
